{"type": "Feature", "id": 12515372, "geometry": {"type": "Point", "coordinates": [19.7204, 52.569]}, "properties": {"woe:id": 12515372, "woe:parent_id": 512781, "woe:name": "Plock Airport", "woe:placetype": 14, "woe:placetype_name": "Airport", "woe:lang": "ENG", "iso:country": "PL", "meta:provider": ["geoplanet:7.3.1", "geoplanet:7.3.2", "geoplanet:7.4.0", "geoplanet:7.4.1", "geoplanet:7.5.1", "geoplanet:7.5.2", "geoplanet:7.6.0", "geoplanet:7.8.1", "geoplanet:7.9.0", "geoplanet:7.10.0", "geoplanet:8.0.0", "woeplanet:8.0.0"], "meta:indexed": "2020-08-20T20:27:53.750458", "meta:updated": "2020-10-14T11:24:16.303960", "woe:hierarchy": {"continent": 24865675, "country": 23424923, "town": 0, "planet": 1, "county": 12591289, "suburb": 0, "state": 12577941, "region": 0, "localadmin": 12618239}, "woe:timezone_id": 28350923, "woe:hash": "u3q509zuweu5", "woe:centroid": [19.7204, 52.569], "geom:latitude": 52.569, "geom:longitude": 19.7204, "geom:hash": "u3q509zuweu5", "woe:latitude": 52.569, "geom:centroid": [19.7204, 52.569], "woe:longitude": 19.7204, "woe:repo": "woeplanet-airport-pl", "geom:area": 0.0, "woe:scale": 19}}