{"type": "Feature", "id": 12515352, "geometry": {"type": "Point", "coordinates": [16.1325, 53.3801]}, "properties": {"woe:id": 12515352, "woe:parent_id": 24933586, "woe:name": "Miroslawiec Highway Strip Airport", "woe:placetype": 14, "woe:placetype_name": "Airport", "woe:lang": "ENG", "iso:country": "PL", "meta:provider": ["geoplanet:7.3.1", "geoplanet:7.3.2", "geoplanet:7.4.0", "geoplanet:7.4.1", "geoplanet:7.5.1", "geoplanet:7.5.2", "geoplanet:7.6.0", "geoplanet:7.8.1", "geoplanet:7.9.0", "geoplanet:7.10.0", "geoplanet:8.0.0", "woeplanet:8.0.0"], "meta:indexed": "2020-08-20T20:27:53.737813", "meta:updated": "2020-10-14T11:24:16.285647", "woe:hierarchy": {"continent": 24865675, "country": 23424923, "town": 0, "planet": 1, "county": 12591490, "suburb": 0, "state": 12577950, "region": 0, "localadmin": 12617325}, "woe:timezone_id": 28350923, "woe:hash": "u37rxje3d7zg", "woe:centroid": [16.1325, 53.3801], "geom:latitude": 53.3801, "geom:longitude": 16.1325, "geom:hash": "u37rxje3d7zg", "woe:latitude": 53.3801, "geom:centroid": [16.1325, 53.3801], "woe:longitude": 16.1325, "woe:repo": "woeplanet-airport-pl", "geom:area": 0.0, "woe:scale": 19}}