{"type": "Feature", "id": 12515390, "properties": {"woe:id": 12515390, "woe:parent_id": 526363, "woe:name": "Strachowice Airport", "woe:placetype": 14, "woe:placetype_name": "Airport", "woe:lang": "ENG", "iso:country": "PL", "meta:provider": ["geoplanet:7.3.1", "geoplanet:7.3.2", "geoplanet:7.4.0", "geoplanet:7.4.1", "geoplanet:7.5.1", "geoplanet:7.5.2", "geoplanet:7.6.0", "geoplanet:7.8.1", "geoplanet:7.9.0", "geoplanet:7.10.0", "geoplanet:8.0.0", "woeplanet:8.0.0"], "meta:indexed": "2020-08-20T20:27:53.792293", "woe:alias_UNK_V": ["Port Lotniczy Wroclaw-Strachowice", "Port Lotniczy Mikolaja Kopernika", "Port Lotniczy Wroclaw"], "woe:alias_ENG_V": ["WRO", "Miedzynarodowy Port Lotniczy", "WRO Airport"], "woe:alias_POL_Q": ["WRO Lotnisko"], "meta:updated": "2020-08-22T01:55:34.554701", "woe:hierarchy": {"continent": 24865675, "country": 23424923, "town": 0, "planet": 1, "county": 12591160, "suburb": 0, "state": 12577935, "region": 0, "localadmin": 12618090}, "woe:timezone_id": 28350923, "woe:hash": "u3h48x3dv7c9", "woe:centroid": [16.89926, 51.104771], "geom:latitude": 51.104771, "geom:longitude": 16.89926, "geom:hash": "u3h48x3dv7c9", "woe:latitude": 51.104771, "geom:centroid": [16.89926, 51.104771], "woe:longitude": 16.89926, "woe:repo": "woeplanet-airport-pl"}, "geometry": {"coordinates": [16.89926, 51.104771], "type": "Point"}}