{"type": "Feature", "id": 12515383, "geometry": {"type": "Point", "coordinates": [19.2024, 50.898102]}, "properties": {"woe:id": 12515383, "woe:parent_id": 501391, "woe:name": "Rudniki Airport", "woe:placetype": 14, "woe:placetype_name": "Airport", "woe:lang": "ENG", "iso:country": "PL", "meta:provider": ["geoplanet:7.3.1", "geoplanet:7.3.2", "geoplanet:7.4.0", "geoplanet:7.4.1", "geoplanet:7.5.1", "geoplanet:7.5.2", "geoplanet:7.6.0", "geoplanet:7.8.1", "geoplanet:7.9.0", "geoplanet:7.10.0", "geoplanet:8.0.0", "woeplanet:8.0.0"], "meta:indexed": "2020-08-20T20:27:53.758962", "woe:alias_ENG_V": ["CZW", "CZW Airport"], "woe:alias_POL_Q": ["CZW Lotnisko"], "meta:updated": "2020-10-14T11:24:16.301145", "woe:hierarchy": {"continent": 24865675, "country": 23424923, "town": 0, "planet": 1, "county": 12591391, "suburb": 0, "state": 12577946, "region": 0, "localadmin": 12618833}, "woe:timezone_id": 28350923, "woe:hash": "u3j9scwybmgh", "woe:centroid": [19.2024, 50.898102], "geom:latitude": 50.898102, "geom:longitude": 19.2024, "geom:hash": "u3j9scwybmgh", "woe:latitude": 50.898102, "geom:centroid": [19.2024, 50.898102], "woe:longitude": 19.2024, "woe:repo": "woeplanet-airport-pl", "geom:area": 0.0, "woe:scale": 19}}