{"type": "Feature", "id": 12515376, "geometry": {"type": "Point", "coordinates": [15.7366, 53.303501]}, "properties": {"woe:id": 12515376, "woe:parent_id": 521194, "woe:name": "Pomorskiwnw Airport", "woe:placetype": 14, "woe:placetype_name": "Airport", "woe:lang": "ENG", "iso:country": "PL", "meta:provider": ["geoplanet:7.3.1", "geoplanet:7.3.2", "geoplanet:7.4.0", "geoplanet:7.4.1", "geoplanet:7.5.1", "geoplanet:7.5.2", "geoplanet:7.6.0", "geoplanet:7.8.1", "geoplanet:7.9.0", "geoplanet:7.10.0", "geoplanet:8.0.0", "woeplanet:8.0.0"], "meta:indexed": "2020-08-20T20:27:53.753863", "meta:updated": "2020-10-14T11:24:16.316961", "woe:hierarchy": {"continent": 24865675, "country": 23424923, "town": 0, "planet": 1, "county": 12591489, "suburb": 0, "state": 12577950, "region": 0, "localadmin": 24547757}, "woe:timezone_id": 28350923, "woe:hash": "u37pnpe53kg2", "woe:centroid": [15.7366, 53.303501], "geom:latitude": 53.303501, "geom:longitude": 15.7366, "geom:hash": "u37pnpe53kg2", "woe:latitude": 53.303501, "geom:centroid": [15.7366, 53.303501], "woe:longitude": 15.7366, "woe:repo": "woeplanet-airport-pl", "geom:area": 0.0, "woe:scale": 19}}