{"type": "Feature", "id": 12523956, "properties": {"woe:id": 12523956, "woe:parent_id": 522891, "woe:name": "Szwederowo Airport", "woe:placetype": 14, "woe:placetype_name": "Airport", "woe:lang": "ENG", "iso:country": "PL", "meta:provider": ["geoplanet:7.3.1", "geoplanet:7.3.2", "geoplanet:7.4.0", "geoplanet:7.4.1", "geoplanet:7.5.1", "geoplanet:7.5.2", "geoplanet:7.6.0", "geoplanet:7.8.1", "geoplanet:7.9.0", "geoplanet:7.10.0", "geoplanet:8.0.0", "woeplanet:8.0.0"], "meta:indexed": "2020-08-20T20:27:53.781191", "woe:alias_ENG_V": ["Szwederowo", "BZG", "BZG Airport"], "woe:alias_POL_Q": ["BZG Lotnisko"], "meta:updated": "2020-08-22T01:55:34.547323", "woe:hierarchy": {"continent": 24865675, "country": 23424923, "town": 0, "planet": 1, "county": 12591167, "suburb": 0, "state": 12577936, "region": 0, "localadmin": 12617468}, "woe:timezone_id": 28350923, "woe:hash": "u3ky11n4m0d4", "woe:centroid": [17.98209, 53.09182], "geom:latitude": 53.09182, "geom:longitude": 17.98209, "geom:hash": "u3ky11n4m0d4", "woe:latitude": 53.09182, "geom:centroid": [17.98209, 53.09182], "woe:longitude": 17.98209, "woe:repo": "woeplanet-airport-pl"}, "geometry": {"coordinates": [17.98209, 53.09182], "type": "Point"}}