{"type": "Feature", "id": 12515399, "geometry": {"type": "Point", "coordinates": [18.730301, 51.708302]}, "properties": {"woe:id": 12515399, "woe:parent_id": 24937563, "woe:name": "Warta Highway Strip Airport", "woe:placetype": 14, "woe:placetype_name": "Airport", "woe:lang": "ENG", "iso:country": "PL", "meta:provider": ["geoplanet:7.3.1", "geoplanet:7.3.2", "geoplanet:7.4.0", "geoplanet:7.4.1", "geoplanet:7.5.1", "geoplanet:7.5.2", "geoplanet:7.6.0", "geoplanet:7.8.1", "geoplanet:7.9.0", "geoplanet:7.10.0", "geoplanet:8.0.0", "woeplanet:8.0.0"], "meta:indexed": "2020-08-20T20:27:53.772017", "meta:updated": "2020-10-14T11:24:16.311629", "woe:hierarchy": {"continent": 24865675, "country": 23424923, "town": 0, "planet": 1, "county": 12591203, "suburb": 0, "state": 12577937, "region": 0, "localadmin": 24548385}, "woe:timezone_id": 28350923, "woe:hash": "u3jq4jnyxwhs", "woe:centroid": [18.730301, 51.708302], "geom:latitude": 51.708302, "geom:longitude": 18.730301, "geom:hash": "u3jq4jnyxwhs", "woe:latitude": 51.708302, "geom:centroid": [18.730301, 51.708302], "woe:longitude": 18.730301, "woe:repo": "woeplanet-airport-pl", "geom:area": 0.0, "woe:scale": 19}}