{"type": "Feature", "id": 12515408, "geometry": {"type": "Point", "coordinates": [19.0772, 50.481899]}, "properties": {"woe:id": 12515408, "woe:parent_id": 528690, "woe:name": "Zendek Airport", "woe:placetype": 14, "woe:placetype_name": "Airport", "woe:lang": "ENG", "iso:country": "PL", "meta:provider": ["geoplanet:7.3.1", "geoplanet:7.3.2", "geoplanet:7.4.0", "geoplanet:7.4.1", "geoplanet:7.5.1", "geoplanet:7.5.2", "geoplanet:7.6.0", "geoplanet:7.8.1", "geoplanet:7.9.0", "geoplanet:7.10.0", "geoplanet:8.0.0", "woeplanet:8.0.0"], "meta:indexed": "2020-08-20T20:27:53.793192", "woe:alias_ENG_V": ["KTW", "KTW Airport"], "woe:alias_POL_Q": ["KTW Lotnisko"], "meta:updated": "2020-10-14T11:24:16.348624", "woe:hierarchy": {"continent": 24865675, "country": 23424923, "town": 0, "planet": 1, "county": 12591412, "suburb": 0, "state": 12577946, "region": 0, "localadmin": 12618156}, "woe:timezone_id": 28350923, "woe:hash": "u2vx4jgw6up3", "woe:centroid": [19.0772, 50.481899], "geom:latitude": 50.481899, "geom:longitude": 19.0772, "geom:hash": "u2vx4jgw6up3", "woe:latitude": 50.481899, "geom:centroid": [19.0772, 50.481899], "woe:longitude": 19.0772, "woe:repo": "woeplanet-airport-pl", "geom:area": 0.0, "woe:scale": 19}}