{"type": "Feature", "id": 12515321, "geometry": {"type": "Point", "coordinates": [17.039101, 52.4244]}, "properties": {"woe:id": 12515321, "woe:parent_id": 514048, "woe:name": "Kobylnica Airport", "woe:placetype": 14, "woe:placetype_name": "Airport", "woe:lang": "ENG", "iso:country": "PL", "meta:provider": ["geoplanet:7.3.1", "geoplanet:7.3.2", "geoplanet:7.4.0", "geoplanet:7.4.1", "geoplanet:7.5.1", "geoplanet:7.5.2", "geoplanet:7.6.0", "geoplanet:7.8.1", "geoplanet:7.9.0", "geoplanet:7.10.0", "geoplanet:8.0.0", "woeplanet:8.0.0"], "meta:indexed": "2020-08-20T20:27:53.716758", "meta:updated": "2020-10-14T11:24:16.295266", "woe:hierarchy": {"continent": 24865675, "country": 23424923, "town": 0, "planet": 1, "county": 12591476, "suburb": 0, "state": 12577949, "region": 0, "localadmin": 12618604}, "woe:timezone_id": 28350923, "woe:hash": "u3k45xx6rb6x", "woe:centroid": [17.039101, 52.4244], "geom:latitude": 52.4244, "geom:longitude": 17.039101, "geom:hash": "u3k45xx6rb6x", "woe:latitude": 52.4244, "geom:centroid": [17.039101, 52.4244], "woe:longitude": 17.039101, "woe:repo": "woeplanet-airport-pl", "geom:area": 0.0, "woe:scale": 19}}