{"type": "Feature", "id": 12515318, "properties": {"woe:id": 12515318, "woe:parent_id": 518021, "woe:name": "Kanice Highway Strip Airport", "woe:placetype": 14, "woe:placetype_name": "Airport", "woe:lang": "ENG", "iso:country": "PL", "meta:provider": ["geoplanet:7.3.1", "geoplanet:7.3.2", "geoplanet:7.4.0", "geoplanet:7.4.1", "geoplanet:7.5.1", "geoplanet:7.5.2", "geoplanet:7.6.0", "geoplanet:7.8.1", "geoplanet:7.9.0", "geoplanet:7.10.0", "geoplanet:8.0.0", "woeplanet:8.0.0"], "meta:indexed": "2020-08-20T20:27:53.714268", "meta:updated": "2020-08-22T01:55:34.509416", "woe:hierarchy": {"continent": 24865675, "country": 23424923, "town": 0, "planet": 1, "county": 12591202, "suburb": 0, "state": 12577937, "region": 0, "localadmin": 12618219}, "woe:timezone_id": 28350923, "woe:hash": "u3nmvtj8d10k", "woe:centroid": [20.288401, 51.6633], "geom:latitude": 51.6633, "geom:longitude": 20.288401, "geom:hash": "u3nmvtj8d10k", "woe:latitude": 51.6633, "geom:centroid": [20.288401, 51.6633], "woe:longitude": 20.288401, "woe:repo": "woeplanet-airport-pl"}, "geometry": {"coordinates": [20.288401, 51.6633], "type": "Point"}}