{"type": "Feature", "id": 12515307, "properties": {"woe:id": 12515307, "woe:parent_id": 529440, "woe:name": "Grojec Airport", "woe:placetype": 14, "woe:placetype_name": "Airport", "woe:lang": "ENG", "iso:country": "PL", "meta:provider": ["geoplanet:7.3.1", "geoplanet:7.3.2", "geoplanet:7.4.0", "geoplanet:7.4.1", "geoplanet:7.5.1", "geoplanet:7.5.2", "geoplanet:7.6.0", "geoplanet:7.8.1", "geoplanet:7.9.0", "geoplanet:7.10.0", "geoplanet:8.0.0", "woeplanet:8.0.0"], "meta:indexed": "2020-08-20T20:27:53.705776", "meta:updated": "2020-08-22T01:55:34.505481", "woe:hierarchy": {"continent": 24865675, "country": 23424923, "town": 0, "planet": 1, "county": 12591275, "suburb": 0, "state": 12577941, "region": 0, "localadmin": 12617204}, "woe:timezone_id": 28350923, "woe:hash": "u3nzhyhzcpux", "woe:centroid": [20.9575, 51.889801], "geom:latitude": 51.889801, "geom:longitude": 20.9575, "geom:hash": "u3nzhyhzcpux", "woe:latitude": 51.889801, "geom:centroid": [20.9575, 51.889801], "woe:longitude": 20.9575, "woe:repo": "woeplanet-airport-pl"}, "geometry": {"coordinates": [20.9575, 51.889801], "type": "Point"}}