{"type": "Feature", "id": 12515343, "properties": {"woe:id": 12515343, "woe:parent_id": 505742, "woe:name": "Lukaszow Airport", "woe:placetype": 14, "woe:placetype_name": "Airport", "woe:lang": "ENG", "iso:country": "PL", "meta:provider": ["geoplanet:7.3.1", "geoplanet:7.3.2", "geoplanet:7.4.0", "geoplanet:7.4.1", "geoplanet:7.5.1", "geoplanet:7.5.2", "geoplanet:7.6.0", "geoplanet:7.8.1", "geoplanet:7.9.0", "geoplanet:7.10.0", "geoplanet:8.0.0", "woeplanet:8.0.0"], "meta:indexed": "2020-08-20T20:27:53.730148", "meta:updated": "2020-08-22T01:55:34.519189", "woe:hierarchy": {"continent": 24865675, "country": 23424923, "town": 0, "planet": 1, "county": 12591164, "suburb": 0, "state": 12577935, "region": 0, "localadmin": 12618095}, "woe:timezone_id": 28350923, "woe:hash": "u3574nb5672n", "woe:centroid": [15.9083, 51.189999], "geom:latitude": 51.189999, "geom:longitude": 15.9083, "geom:hash": "u3574nb5672n", "woe:latitude": 51.189999, "geom:centroid": [15.9083, 51.189999], "woe:longitude": 15.9083, "woe:repo": "woeplanet-airport-pl"}, "geometry": {"coordinates": [15.9083, 51.189999], "type": "Point"}}